<?xml version="1.0" encoding="utf-8"?>
<odoo>

    <record id="view_document_type_merge_wizard" model="ir.ui.view">
        <field name="name">res.partner.document.type.merge.wizard</field>
        <field name="model">res.partner.document.type.merge</field>
        <field name="type">form</field>
        <field name="arch" type="xml">
            <form string=" Merge ">
                <notebook>
                    <page string="Items">
                        <field name="item_ids" nolabel="1" colspan="2">
                            <list create="false" edit="0" delete="0">
                                <field name="name"/>
                                <field name="category_id"/>
                            </list>
                        </field>
                    </page>
                </notebook>
                <footer>
                    <button name="action_merge" string="Merge" type="object" class="oe_highlight"/>
                    <button special="cancel" string="Cancel" class="oe_link"/>
                </footer>
            </form>
        </field>
    </record>

    <record id="action_merge_lines" model="ir.actions.act_window">
        <field name="name">Merge</field>
        <field name="type">ir.actions.act_window</field>
        <field name="res_model">res.partner.document.type.merge</field>
        <field name="view_mode">form</field>
        <field name="view_id" ref="view_document_type_merge_wizard"/>
        <field name="target">new</field>
        <field name="binding_model_id" ref="model_res_partner_document_type"/>
    </record>

</odoo>

