<odoo>
    <record id="reached_checkpoint_form" model="ir.ui.view">
        <field name="name">reached.checkpoint.form</field>
        <field name="model">reached.checkpoint</field>
        <field name="arch" type="xml">
            <form string="">
                <sheet>
                    <group>
                        <field name="name"/>
                    </group>
                </sheet>
            </form>
        </field>
    </record>
    <record id="reached_checkpoint_tree" model="ir.ui.view">
        <field name="name">reached.checkpoint.tree</field>
        <field name="model">reached.checkpoint</field>
        <field name="arch" type="xml">
            <list string="">
                <field name="name"/>
            </list>
        </field>
    </record>
    <record id="reached_checkpoint_search" model="ir.ui.view">
        <field name="name">reached.checkpoint.search</field>
        <field name="model">reached.checkpoint</field>
        <field name="arch" type="xml">
            <search string="">
                <field name="name"/>
            </search>
        </field>
    </record>


    <record id="hand_legal_type_tree" model="ir.ui.view">
        <field name="name">Legal Type Tree</field>
        <field name="model">hand.legal.type</field>
        <field name="arch" type="xml">
            <list editable="bottom">
                <field name="name"/>
                <field name="license_authority_ids" widget="many2many_tags"/>
            </list>
        </field>
    </record>
    <record id="hand_legal_type_action" model="ir.actions.act_window">
        <field name="name">Legal Type</field>
        <field name="type">ir.actions.act_window</field>
        <field name="res_model">hand.legal.type</field>
        <field name="view_mode">list</field>
    </record>
    <menuitem id="hand_legal_type_menu" name="Legal Type"
              parent="contacts.res_partner_menu_config"
              action="hand_legal_type_action" sequence="52"/>
</odoo>